decode_reg_inst.sv

`ifndef FILE_INCL
    `include "processor_defines.sv"
`endif

module decode_reg_inst(
    input logic [31:7] instruction_code,
    output logic [4:0] rs1,
    output logic [4:0] rs2,
    output logic [4:0] rd,
    output logic [4:0] alu_control
);

logic [31:25] func7;
logic [14:12] func3;





always_comb
begin
 func3=instruction_code[14:12];
 func7=instruction_code[31:25];
 rd=instruction_code[11:7];
 rs1= instruction_code[19:15];
 rs2 = instruction_code[24:20];

    if(func3==3'h0)
    begin
        if(func7==7'h00)
        begin
            alu_control= `ADD;
        end
        else
        begin
            alu_control= `SUB;
        end
    end

    else if(func3==3'h1)
    begin
        alu_control= `SLL;
    end

    else if(func3==3'h2)
    begin
        alu_control= `SLT;
    end

    else if(func3==3'h3)
    begin
        alu_control= `SLTU;
    end

    else if(func3==3'h4)
    begin
        alu_control= `XOR;
    end

    else if(func3==3'h5)
    begin
        if(func7==7'h00)
        begin
            alu_control= `SRL;
        end
        else
        begin
            alu_control= `SRA;
        end
    end

    else if(func3==3'h6)
    begin
        alu_control= `OR;
    end

    else if(func3==3'h7)
    begin
        alu_control= `AND;
    end  

    

end

`ifndef SUBMODULE_DISABLE_WAVES
   initial
     begin
        $dumpfile("./sim_build/decode_reg_inst.vcd");
        $dumpvars(0, decode_reg_inst);
     end
 `endif

endmodule

decode_reg_inst.vcd
$date
	Mon Jul  1 12:58:55 2024
$end
$version
	Icarus Verilog
$end
$timescale
	1ps
$end
$scope module decode_reg_inst $end
$var wire 25 ! instruction_code [31:7] $end
$var reg 5 " alu_control [4:0] $end
$var reg 3 # func3 [14:12] $end
$var reg 7 $ func7 [31:25] $end
$var reg 5 % rd [4:0] $end
$var reg 5 & rs1 [4:0] $end
$var reg 5 ' rs2 [4:0] $end
$upscope $end
$enddefinitions $end
$comment Show the parameter values. $end
$dumpall
$end
#0
$dumpvars
b11011 '
b11001 &
b11010 %
b1011011 $
b110 #
b100 "
b1011011110111100111011010 !
$end
#1000
b10111 '
b1011 &
b11001 %
b1100000 $
b1100000101110101111011001 !
#2000
b1010 "
b11100 '
b10111 &
b1100 $
b11 #
b1100111001011101111001 !
#3000
b101 "
b100 '
b101 &
b1000 %
b101000 $
b111 #
b101000001000010111101000 !
#4000
b100 "
b10001 '
b1001 &
b1 %
b1011 $
b110 #
b1011100010100111000001 !
#5000
b11010 '
b1110 &
b10011 %
b110 $
b110110100111011010011 !
#6000
b101 "
b10 '
b11101 &
b110 %
b10000 $
b111 #
b10000000101110111100110 !
#7000
b1000 "
b10111 '
b1010 &
b11001 %
b101111 $
b101 #
b101111101110101010111001 !
#8000
b10 "
b11001 '
b1111 &
b1011 %
b111000 $
b0 #
b111000110010111100001011 !
#9000
b1010 "
b101 '
b1 &
b10011 %
b1100010 $
b11 #
b1100010001010000101110011 !
#10000
b11 "
b10000 '
b10101 &
b10001 %
b1000000 $
b100 #
b1000000100001010110010001 !
#11000
b110 "
b1110 '
b10110 &
b11011 $
b1 #
b11011011101011000110001 !
#12000
b11 "
b10111 '
b10010 %
b1010101 $
b100 #
b1010101101111011010010010 !
#13000
b110 "
b1000 '
b11101 &
b11110 %
b110011 $
b1 #
b110011010001110100111110 !
#14000
b1000 "
b100 '
b10100 &
b11010 %
b1011100 $
b101 #
b1011100001001010010111010 !
#15000
b1010 "
b1110 '
b1 &
b10 %
b1 $
b11 #
b1011100000101100010 !
#16000
b10 "
b11100 '
b10100 &
b11100 %
b11011 $
b0 #
b11011111001010000011100 !
#17000
b11 "
b10001 '
b110 &
b10011 %
b10100 $
b100 #
b10100100010011010010011 !
#18000
b1010 "
b11 '
b10110 &
b10100 %
b11100 $
b11 #
b11100000111011001110100 !
#19000
b101 "
b0 &
b11100 %
b1101000 $
b111 #
b1101000000110000011111100 !
#20000
b110 "
b11000 '
b110 &
b110 %
b1110100 $
b1 #
b1110100110000011000100110 !
#21000
b1001 "
b10110 '
b11 &
b11100 %
b1110011 $
b10 #
b1110011101100001101011100 !
#22000
b1000 "
b101 '
b11000 &
b1 %
b100110 $
b101 #
b100110001011100010100001 !
#23000
b11 "
b10110 '
b10110 &
b10011 %
b1 $
b100 #
b1101101011010010011 !
#24000
b10 "
b1000 '
b1011 &
b10000 %
b1101010 $
b0 #
b1101010010000101100010000 !
#25000
b100 "
b11011 '
b1110 &
b101 %
b1111011 $
b110 #
b1111011110110111011000101 !
#26000
b1001 "
b11 '
b11110 &
b1110 %
b1101101 $
b10 #
b1101101000111111001001110 !
#27000
b10 "
b10011 '
b1101 &
b1100100 $
b0 #
b1100100100110110100001110 !
#28000
b101 "
b1111 '
b1000 &
b10000 %
b1011010 $
b111 #
b1011010011110100011110000 !
#29000
b1001 "
b10001 '
b10101 &
b1110 %
b11101 $
b10 #
b11101100011010101001110 !
#30000
b11 "
b1000 '
b111 &
b10111 %
b1110001 $
b100 #
b1110001010000011110010111 !
#31000
b110 "
b1 '
b10110 &
b11001 %
b100111 $
b1 #
b100111000011011000111001 !
#32000
b10 "
b101 '
b101 &
b11000 %
b1101111 $
b0 #
b1101111001010010100011000 !
#33000
b10 '
b11000 &
b11010 %
b1010011 $
b1010011000101100000011010 !
#34000
b11 "
b11001 '
b0 &
b10011 %
b110001 $
b100 #
b110001110010000010010011 !
#35000
b1000 "
b11011 '
b11011 &
b11000 %
b1001001 $
b101 #
b1001001110111101110111000 !
#36000
b1010 "
b100 '
b11 &
b10000 %
b110 $
b11 #
b110001000001101110000 !
#37000
b111 "
b101 '
b10010 &
b11011 %
b0 $
b101 #
b1011001010111011 !
#38000
b11 "
b10101 '
b10110 &
b1010 %
b101011 $
b100 #
b101011101011011010001010 !
#39000
b100 "
b110 '
b1111 &
b10101 %
b1101111 $
b110 #
b1101111001100111111010101 !
#40000
b1010 "
b101 '
b1011 &
b11001 %
b11 #
b1101111001010101101111001 !
#41000
b10 "
b10 '
b10 &
b10011 %
b100101 $
b0 #
b100101000100001000010011 !
#42000
b100 "
b1000 '
b1110 &
b111 %
b1010011 $
b110 #
b1010011010000111011000111 !
#43000
b101 "
b11111 '
b11010 &
b101 %
b11011 $
b111 #
b11011111111101011100101 !
#44000
b1001 "
b0 '
b1001 &
b11101 %
b1000011 $
b10 #
b1000011000000100101011101 !
#45000
b1010 "
b10010 '
b11110 &
b1000 %
b11 #
b1000011100101111001101000 !
#46000
b100 "
b1 '
b0 &
b1001 %
b110010 $
b110 #
b110010000010000011001001 !
#47000
b101 "
b10011 '
b1111 &
b11000 %
b1110010 $
b111 #
b1110010100110111111111000 !
#48000
b1001 "
b10111 '
b11000 &
b11101 %
b110100 $
b10 #
b110100101111100001011101 !
#49000
b11 "
b11110 '
b11110 &
b11010 %
b1111100 $
b100 #
b1111100111101111010011010 !
#50000
b1001 "
b11101 '
b110 &
b11110 %
b1001001 $
b10 #
b1001001111010011001011110 !
#51000
b10 "
b11110 '
b1011 &
b1101 %
b1001000 $
b0 #
b1001000111100101100001101 !
#52000
b101 "
b1 '
b11101 &
b10000 %
b1111110 $
b111 #
b1111110000011110111110000 !
#53000
b10 "
b1110 '
b11000 &
b11011 %
b1110010 $
b0 #
b1110010011101100000011011 !
#54000
b1000 "
b11 &
b11000 %
b101 #
b1110010011100001110111000 !
#55000
b101 "
b111 '
b1011 &
b11011 %
b1101011 $
b111 #
b1101011001110101111111011 !
#56000
b1001 "
b11101 '
b111 &
b11000 %
b101011 $
b10 #
b101011111010011101011000 !
#57000
b110 "
b10110 '
b1111 &
b10110 %
b1100001 $
b1 #
b1100001101100111100110110 !
#58000
b10010 '
b110 &
b100 %
b1101101 $
b1101101100100011000100100 !
#59000
b11101 '
b11010 &
b11101 %
b1010101 $
b1010101111011101000111101 !
#60000
b11 "
b10 '
b101 &
b11010 %
b10001 $
b100 #
b10001000100010110011010 !
#61000
b100 "
b11 '
b10110 &
b11100 %
b111111 $
b110 #
b111111000111011011011100 !
#62000
b1010 '
b1101 &
b1011 %
b1111001 $
b1111001010100110111001011 !
#63000
b101 "
b10000 '
b1110 &
b10100 %
b10000 $
b111 #
b10000100000111011110100 !
#64000
b10011 '
b1100 &
b10 %
b1111100 $
b1111100100110110011100010 !
#65000
b10 "
b1000 '
b1 &
b1001 %
b1010000 $
b0 #
b1010000010000000100001001 !
#66000
b1010 "
b11110 '
b1100 &
b10011 %
b10110 $
b11 #
b10110111100110001110011 !
#67000
b110 "
b1101 '
b11111 &
b11011 %
b101011 $
b1 #
b101011011011111100111011 !
#68000
b10 "
b110 '
b10100 &
b1101 %
b1100000 $
b0 #
b1100000001101010000001101 !
#69000
b100 "
b10001 '
b1111 &
b1100 %
b1111111 $
b110 #
b1111111100010111111001100 !
#70000
b1001 "
b10 '
b10000 &
b110 %
b1001100 $
b10 #
b1001100000101000001000110 !
#71000
b100 "
b11100 &
b11101 %
b1111001 $
b110 #
b1111001000101110011011101 !
#72000
b101 "
b1110 '
b10010 &
b1010 %
b110001 $
b111 #
b110001011101001011101010 !
#73000
b11 "
b111 '
b1011 &
b111 %
b1100 $
b100 #
b1100001110101110000111 !
#74000
b110 "
b11010 '
b1010 &
b1000 %
b1110111 $
b1 #
b1110111110100101000101000 !
#75000
b1001 "
b10010 '
b0 &
b11010 %
b11100 $
b10 #
b11100100100000001011010 !
#76000
b100 "
b11100 '
b111 &
b1111 %
b10000 $
b110 #
b10000111000011111001111 !
#77000
b1000 "
b1000 &
b1110 %
b1011010 $
b101 #
b1011010111000100010101110 !
#78000
b1001 "
b10110 '
b10011 &
b100 %
b110001 $
b10 #
b110001101101001101000100 !
#79000
b1 '
b10000 &
b11110 %
b1100101 $
b1100101000011000001011110 !
#80000
b101 "
b10100 '
b1000 &
b1101 %
b11101 $
b111 #
b11101101000100011101101 !
#81000
b1001 "
b100 '
b10100 &
b111 %
b1010010 $
b10 #
b1010010001001010001000111 !
#82000
b110 "
b10110 '
b10011 &
b10101 %
b101010 $
b1 #
b101010101101001100110101 !
#83000
b10010 '
b10111 &
b1110 %
b11101 $
b11101100101011100101110 !
#84000
b1000 "
b1101 '
b11100 &
b10101 %
b1101010 $
b101 #
b1101010011011110010110101 !
#85000
b110 "
b11111 '
b10111 &
b11111 %
b110100 $
b1 #
b110100111111011100111111 !
#86000
b11000 '
b11111 &
b1010 %
b1001110 $
b1001110110001111100101010 !
#87000
b100 "
b1000 '
b0 &
b1001 %
b110111 $
b110 #
b110111010000000011001001 !
#88000
b1001 "
b1 '
b11 &
b101 %
b1000111 $
b10 #
b1000111000010001101000101 !
#89000
b100 "
b11010 '
b0 &
b10111 %
b1010001 $
b110 #
b1010001110100000011010111 !
#90000
b110 "
b11110 '
b111 &
b11111 %
b10111 $
b1 #
b10111111100011100111111 !
#91000
b11000 '
b10111 &
b10111 %
b110101 $
b110101110001011100110111 !
#92000
b1010 "
b1011 '
b100 &
b110 %
b1000011 $
b11 #
b1000011010110010001100110 !
#93000
b10 "
b10 '
b1110 &
b10011 %
b1111111 $
b0 #
b1111111000100111000010011 !
#94000
b1000 "
b11101 '
b1011 &
b11100 %
b1010000 $
b101 #
b1010000111010101110111100 !
#95000
b101 "
b10011 '
b10011 &
b1111 %
b1000100 $
b111 #
b1000100100111001111101111 !
#96000
b11111 '
b10110 &
b10011 %
b1101 $
b1101111111011011110011 !
#97000
b1000 "
b0 '
b10001 &
b11000 %
b1011011 $
b101 #
b1011011000001000110111000 !
#98000
b100 "
b11010 '
b10101 &
b10000 %
b101110 $
b110 #
b101110110101010111010000 !
#99000
b1010 "
b0 &
b11100 %
b1110101 $
b11 #
b1110101110100000001111100 !
