ifu.sv

module ifu(
    input logic i_clk,
    input logic i_rst,
    input logic stall_pc,
    input logic pc_update_control,
    input logic [31:0] pc_update_val,
    output logic [31:0] pc,
    output logic [31:0] prev_pc
);

always@ (posedge i_clk or negedge i_rst)
begin
   if(~ i_rst)
   begin
      pc <=0;
      prev_pc <=0;
   end
   else   
   case(stall_pc)
      1'b1: pc<= pc;
      1'b0: case(pc_update_control)
               1'b1: pc <= pc_update_val;
               1'b0: pc <= pc+4;
            endcase
   endcase
end

`ifndef SUBMODULE_DISABLE_WAVES
   initial
     begin
        $dumpfile("./sim_build/ifu.vcd");
        $dumpvars(0, ifu);
     end
`endif

endmodule

ifu.vcd
$date
	Mon Jul  1 15:11:31 2024
$end
$version
	Icarus Verilog
$end
$timescale
	1ps
$end
$scope module ifu $end
$var wire 1 ! i_clk $end
$var wire 1 " i_rst $end
$var wire 1 # pc_update_control $end
$var wire 32 $ pc_update_val [31:0] $end
$var wire 1 % stall_pc $end
$var reg 32 & pc [31:0] $end
$var reg 32 ' prev_pc [31:0] $end
$upscope $end
$enddefinitions $end
$comment Show the parameter values. $end
$dumpall
$end
#0
$dumpvars
bx '
bx &
0%
b0 $
0#
1"
0!
$end
#5000
1!
#5500
b0 '
b0 &
0"
0!
#6000
1!
#6500
0!
#7000
1"
1!
#7500
0!
#8000
b100 &
1!
#8100
b101000 $
1#
1%
#8500
0!
#9000
1!
#9100
b111100 $
0%
#9500
0!
#10000
b111100 &
1!
#10100
b1001100 $
0#
#10500
0!
#11000
b1000000 &
1!
#11100
b1101000 $
#11500
0!
#12000
b1000100 &
1!
#12100
b10010000 $
#12500
0!
#13000
b1001000 &
1!
#13100
b1010000 $
1#
1%
#13500
0!
#14000
1!
#14100
b10011000 $
0#
0%
#14500
0!
#15000
b1001100 &
1!
#15100
b1110000 $
1#
#15500
0!
#16000
b1110000 &
1!
#16100
b10001100 $
1%
#16500
0!
#17000
1!
#17100
b11101000 $
0%
#17500
0!
#18000
b11101000 &
1!
#18100
b100101000 $
1%
#18500
0!
#19000
1!
#19100
b100111000 $
#19500
0!
#20000
1!
#20100
b11110000 $
0#
#20500
0!
#21000
1!
#21100
1#
0%
#21500
0!
#22000
b11110000 &
1!
#22100
b100010000 $
0#
1%
#22500
0!
#23000
1!
#23100
b100110100 $
1#
0%
#23500
0!
#24000
b100110100 &
1!
#24100
b101100000 $
0#
#24500
0!
#25000
b100111000 &
1!
#25100
b101010100 $
1#
1%
#25500
0!
#26000
1!
#26100
b110100000 $
#26500
0!
#27000
1!
#27100
b101100100 $
0%
#27500
0!
#28000
b101100100 &
1!
#28100
b111000000 $
1%
#28500
0!
#29000
1!
#29100
b110011100 $
#29500
0!
#30000
1!
#30100
b110010000 $
0#
#30500
0!
#31000
1!
#31100
b110000100 $
0%
#31500
0!
#32000
b101101000 &
1!
#32100
b110101000 $
1#
1%
#32500
0!
#33000
1!
#33100
b111100000 $
0%
#33500
0!
#34000
b111100000 &
1!
#34100
b1000001100 $
0#
1%
#34500
0!
#35000
1!
#35100
b1000001000 $
0%
#35500
0!
#36000
b111100100 &
1!
#36100
b1000001100 $
#36500
0!
#37000
b111101000 &
1!
#37100
b1001011100 $
1#
1%
#37500
0!
#38000
1!
#38100
b1000111100 $
0#
#38500
0!
#39000
1!
#39500
0!
#40000
1!
#40100
b1001000000 $
1#
0%
#40500
0!
#41000
b1001000000 &
1!
#41100
b1010000000 $
1%
#41500
0!
#42000
1!
#42100
b1010110100 $
0%
#42500
0!
#43000
b1010110100 &
1!
#43100
b1011010100 $
#43500
0!
#44000
b1011010100 &
1!
#44100
b1101010000 $
#44500
0!
#45000
b1101010000 &
1!
#45100
b1110101100 $
0#
#45500
0!
#46000
b1101010100 &
1!
#46100
b1111010000 $
1%
#46500
0!
#47000
1!
#47100
b1101011100 $
1#
#47500
0!
#48000
1!
#48100
b1111000100 $
0#
#48500
0!
#49000
1!
#49100
b1110011000 $
#49500
0!
#50000
1!
#50100
1#
0%
#50500
0!
#51000
b1110011000 &
1!
#51100
b10000001000 $
1%
#51500
0!
#52000
1!
#52100
b10000010100 $
0%
#52500
0!
#53000
b10000010100 &
1!
#53100
b10010001000 $
0#
1%
#53500
0!
#54000
1!
#54100
b10001110100 $
#54500
0!
#55000
1!
#55100
b10000011000 $
#55500
0!
#56000
1!
#56100
b10001111100 $
#56500
0!
#57000
1!
#57100
b10001101000 $
#57500
0!
#58000
1!
#58100
b10010000100 $
#58500
0!
#59000
1!
#59100
b10000110000 $
1#
#59500
0!
#60000
1!
#60100
b10001001100 $
#60500
0!
#61000
1!
#61100
b10000110100 $
0#
0%
#61500
0!
#62000
b10000011000 &
1!
#62100
b10001000000 $
1%
#62500
0!
#63000
1!
#63100
b10000100000 $
1#
#63500
0!
#64000
1!
#64100
0%
#64500
0!
#65000
b10000100000 &
1!
#65100
b10001111100 $
0#
#65500
0!
#66000
b10000100100 &
1!
#66100
b10010001000 $
1#
#66500
0!
#67000
b10010001000 &
1!
#67100
b10010100000 $
1%
#67500
0!
#68000
1!
#68100
b10100000100 $
0#
0%
#68500
0!
#69000
b10010001100 &
1!
#69100
b10010010000 $
#69500
0!
#70000
b10010010000 &
1!
#70100
b10011101100 $
1%
#70500
0!
#71000
1!
#71100
b10011011100 $
#71500
0!
#72000
1!
#72100
b10011111100 $
#72500
0!
#73000
1!
#73100
b10010110100 $
1#
0%
#73500
0!
#74000
b10010110100 &
1!
#74100
b10011001100 $
#74500
0!
#75000
b10011001100 &
1!
#75100
b10011011000 $
0#
1%
#75500
0!
#76000
1!
#76100
b10100000100 $
0%
#76500
0!
#77000
b10011010000 &
1!
#77100
b10100010100 $
1#
#77500
0!
#78000
b10100010100 &
1!
#78100
b10110000000 $
1%
#78500
0!
#79000
1!
#79100
b10101101100 $
0#
#79500
0!
#80000
1!
#80100
b10101110000 $
#80500
0!
#81000
1!
#81100
b10100100000 $
0%
#81500
0!
#82000
b10100011000 &
1!
#82100
b10110000000 $
1#
1%
#82500
0!
#83000
1!
#83100
b10101101000 $
#83500
0!
#84000
1!
#84100
b10110000000 $
0#
#84500
0!
#85000
1!
#85100
b10100111000 $
1#
#85500
0!
#86000
1!
#86100
b10101110100 $
0#
#86500
0!
#87000
1!
#87100
b10100111100 $
1#
0%
#87500
0!
#88000
b10100111100 &
1!
#88100
b10110001000 $
0#
1%
#88500
0!
#89000
1!
#89100
b10101101000 $
1#
#89500
0!
#90000
1!
#90100
b10110011000 $
0%
#90500
0!
#91000
b10110011000 &
1!
#91100
b10111110100 $
0#
#91500
0!
#92000
b10110011100 &
1!
#92100
b10111111100 $
1#
#92500
0!
#93000
b10111111100 &
1!
#93100
b11001011100 $
0#
#93500
0!
#94000
b11000000000 &
1!
#94100
b11000001100 $
1%
#94500
0!
#95000
1!
#95100
b11000011000 $
1#
#95500
0!
#96000
1!
#96100
0%
#96500
0!
#97000
b11000011000 &
1!
#97100
b11000100100 $
1%
#97500
0!
#98000
1!
#98100
b11010001000 $
0#
0%
#98500
0!
#99000
b11000011100 &
1!
#99100
b11001001100 $
1%
#99500
0!
#100000
1!
#100100
b11001000000 $
#100500
0!
#101000
1!
#101100
b11001000100 $
#101500
0!
#102000
1!
#102100
b11001010000 $
1#
0%
#102500
0!
#103000
b11001010000 &
1!
#103100
b11011000100 $
1%
#103500
0!
#104000
1!
#104100
b11011000000 $
0#
#104500
0!
#105000
1!
#105100
b11001101100 $
1#
#105500
0!
#106000
1!
#106100
b11001110000 $
0#
0%
#106500
0!
#107000
b11001010100 &
1!
