jump.sv
`ifndef FILE_INCL
    `include "processor_defines.sv"
`endif

module jump(
    input logic i_clk,
    input logic i_rst,
    input logic [31:0] pc,
    input logic [31:0] imm,
    input logic [31:0] rs1_val,
    input logic [1:0] jump_control,

    output logic rd_write_control,
    output logic [31:0] rd_write_val,
    output logic pc_update_control,
    output logic [31:0] pc_update_val,
    output logic ignore_curr_inst
);

always@(*) begin 
    if(jump_control != `JMP_NOP) begin
        pc_update_control = 'b1;
        rd_write_control = 'b1;
        rd_write_val = pc + 4;
        if(jump_control == `JAL) begin
            pc_update_val = pc + imm;

        end
        else if (jump_control == `JALR) begin
            pc_update_val = rs1_val + imm; 

    end

    end
    else begin
        pc_update_control = 'b0;
        pc_update_val = 'b0;
        rd_write_control = 'b0;
        rd_write_val = 'b0;

    end

end
always@(posedge i_clk or negedge i_rst) begin
    if(~i_rst) begin
        ignore_curr_inst <= 'b0;
    end

    else begin
    ignore_curr_inst <= pc_update_control;
    end
end

`ifndef SUBMODULE_DISABLE_WAVES
   initial
     begin
        $dumpfile("./sim_build/jump.vcd");
        $dumpvars(0, jump);
     end
 `endif

endmodule

jump.vcd
$date
	Tue Jul  2 14:00:26 2024
$end
$version
	Icarus Verilog
$end
$timescale
	1ps
$end
$scope module jump $end
$var wire 1 ! i_clk $end
$var wire 1 " i_rst $end
$var wire 32 # imm [31:0] $end
$var wire 2 $ jump_control [1:0] $end
$var wire 32 % pc [31:0] $end
$var wire 32 & rs1_val [31:0] $end
$var reg 1 ' ignore_curr_inst $end
$var reg 1 ( pc_update_control $end
$var reg 32 ) pc_update_val [31:0] $end
$var reg 1 * rd_write_control $end
$var reg 32 + rd_write_val [31:0] $end
$upscope $end
$enddefinitions $end
$comment Show the parameter values. $end
$dumpall
$end
#0
$dumpvars
b0 +
0*
b0 )
0(
x'
b0 &
b0 %
b0 $
b0 #
1"
0!
$end
#5000
0'
1!
#5500
0"
0!
#6000
1!
#6500
0!
#7000
1"
1!
#7500
0!
#8000
1!
#8100
b110001100000011111100100011100 )
b110001100000011111000101101000 +
1*
1(
b1 $
b11110111000 #
b110111100010111010100100110101 &
b110001100000011111000101100100 %
#8500
0!
#9000
b0 +
0*
b0 )
0(
b0 $
b0 #
b0 &
b110001100000011111000101101000 %
1'
1!
#9500
0!
#10000
0'
1!
#10100
b110101000111 #
b110001110110111100010110100000 &
b111011001010011000100010101111 %
#10500
0!
#11000
1!
#11100
b10011110011111000010111001100 )
b111000111001010100101110000000 +
1*
1(
b10 $
b10000001 #
b10011110011111000010101001011 &
b111000111001010100101101111100 %
#11500
0!
#12000
b0 +
0*
b0 )
0(
b0 $
b0 #
b0 &
b111000111001010100101110000000 %
1'
1!
#12500
0!
#13000
0'
1!
#13100
b11001100100101100100001111000 )
b11001100100101011110000011100 +
1*
1(
b1 $
b110001100000 #
b110000001001101101101100100000 &
b11001100100101011110000011000 %
#13500
0!
#14000
b0 +
0*
b0 )
0(
b0 $
b0 #
b0 &
b11001100100101011110000011100 %
1'
1!
#14500
0!
#15000
0'
1!
#15100
b100110111010100010000000011100 )
b101001011011111111111110010010 +
1*
1(
b10 $
b10100011001 #
b100110111010100001101100000011 &
b101001011011111111111110001110 %
#15500
0!
#16000
b0 +
0*
b0 )
0(
b0 $
b0 #
b0 &
b101001011011111111111110010010 %
1'
1!
#16500
0!
#17000
0'
1!
#17100
b101000100000100010011110100011 )
b101000100000100001110110101011 +
1*
1(
b1 $
b100111111100 #
b11111011000010001111111110010 &
b101000100000100001110110100111 %
#17500
0!
#18000
b0 +
0*
b0 )
0(
b0 $
b0 #
b0 &
b101000100000100001110110101011 %
1'
1!
#18500
0!
#19000
0'
1!
#19100
b101001000010011110001010011101 )
b101001000010011101011101111000 +
1*
1(
b1 $
b101100101001 #
b110110001100011010111101111111 &
b101001000010011101011101110100 %
#19500
0!
#20000
b0 +
0*
b0 )
0(
b0 $
b0 #
b0 &
b101001000010011101011101111000 %
1'
1!
#20500
0!
#21000
0'
1!
#21100
b11111111000001111111001100111 )
b11111111000001111100101101110 +
1*
1(
b1 $
b10011111101 #
b10001101101010011000010110001 &
b11111111000001111100101101010 %
#21500
0!
#22000
b0 +
0*
b0 )
0(
b0 $
b0 #
b0 &
b11111111000001111100101101110 %
1'
1!
#22500
0!
#23000
0'
1!
#23100
b101000101101 #
b11001101111110100111110011000 &
b111001100010110011011111101000 %
#23500
0!
#24000
1!
#24100
b11011101010111001010101101010 )
b11011101010111000100010111001 +
1*
1(
b1 $
b110010110101 #
b10011101101000011110101110 &
b11011101010111000100010110101 %
#24500
0!
#25000
b0 +
0*
b0 )
0(
b0 $
b0 #
b0 &
b11011101010111000100010111001 %
1'
1!
#25500
0!
#26000
0'
1!
#26100
b100010101011 #
b1010000100100101101000111 &
b11001001111000111001101011001 %
#26500
0!
#27000
1!
#27100
b100111101001101101101101110100 )
b1011101111111110110100010111 +
1*
1(
b10 $
b1100010001 #
b100111101001101101100001100011 &
b1011101111111110110100010011 %
#27500
0!
#28000
b0 +
0*
b0 )
0(
b0 $
b0 #
b0 &
b1011101111111110110100010111 %
1'
1!
#28500
0!
#29000
0'
1!
#29100
b11100110011 #
b110110100111100111100010101111 &
b10010000011101110000011100 %
#29500
0!
#30000
1!
#30100
b110100110101 #
b100110100000110100011100000100 &
b101100001100100101001100010100 %
#30500
0!
#31000
1!
#31100
b10000110100 #
b1011101011001110000110101 &
b111100001000001111110110110 %
#31500
0!
#32000
1!
#32100
b10111110 #
b110001011101101001100011110 &
b110101100100100010011111110011 %
#32500
0!
#33000
1!
#33100
b100001001110 #
b10011111011001010100100100101 &
b111101101110111110101011110001 %
#33500
0!
#34000
1!
#34100
b110101000011011011011001101100 )
b110101000011011010011101001000 +
1*
1(
b1 $
b111100101000 #
b10011010010110010101100001101 &
b110101000011011010011101000100 %
#34500
0!
#35000
b0 +
0*
b0 )
0(
b0 $
b0 #
b0 &
b110101000011011010011101001000 %
1'
1!
#35500
0!
#36000
0'
1!
#36100
b1011010001 #
b111001011000111011010111100111 &
b111010111001010011000010100000 %
#36500
0!
#37000
1!
#37100
b110001100010010000111111111000 )
b1101110001100001010100100111 +
1*
1(
b10 $
b110001100101 #
b110001100010010000001110010011 &
b1101110001100001010100100011 %
#37500
0!
#38000
b0 +
0*
b0 )
0(
b0 $
b0 #
b0 &
b1101110001100001010100100111 %
1'
1!
#38500
0!
#39000
0'
1!
#39100
b101111011000 #
b111110101100000100000111000010 &
b100101110011001100101111101011 %
#39500
0!
#40000
1!
#40100
b101111101000101101010111000110 )
b101111101000101101001100100110 +
1*
1(
b1 $
b1010100100 #
b1010101110100001111111111 &
b101111101000101101001100100010 %
#40500
0!
#41000
b0 +
0*
b0 )
0(
b0 $
b0 #
b0 &
b101111101000101101001100100110 %
1'
1!
#41500
0!
#42000
0'
1!
#42100
b1000101100010000001100010000 )
b110111010011000001100100111 +
1*
1(
b10 $
b110001111100 #
b1000101100001111011010010100 &
b110111010011000001100100011 %
#42500
0!
#43000
b0 +
0*
b0 )
0(
b0 $
b0 #
b0 &
b110111010011000001100100111 %
1'
1!
#43500
0!
#44000
0'
1!
#44100
b100101100100 #
b111011111111100001111000010111 &
b100110110111001010101111011111 %
#44500
0!
#45000
1!
#45100
b100101101010 #
b110101001011000100001111010010 &
b1000100111010101111100111110 %
#45500
0!
#46000
1!
#46100
b10010010110 #
b100100010100000111100010111101 &
b100010010001011110011101100111 %
#46500
0!
#47000
1!
#47100
b11001011001 #
b110111001100010000011111011000 &
b1101001100100000001100011010 %
#47500
0!
#48000
1!
#48100
b111100110010 #
b101011000010010100101101001 &
b11010000001111110010110101000 %
#48500
0!
#49000
1!
#49100
b10111000100111110101111011011 )
b10111000100111101110001100111 +
1*
1(
b1 $
b111101111000 #
b100110101011010101001101001011 &
b10111000100111101110001100011 %
#49500
0!
#50000
b0 +
0*
b0 )
0(
b0 $
b0 #
b0 &
b10111000100111101110001100111 %
1'
1!
#50500
0!
#51000
0'
1!
#51100
b101101001100 #
b101101011110101101000110000011 &
b100110011011001001010101011110 %
#51500
0!
#52000
1!
#52100
b10111010011 #
b111010111010001001110110101011 &
b111010101000101101001010110011 %
#52500
0!
#53000
1!
#53100
b100000111010010001010001010010 )
b101001101101100010111111101101 +
1*
1(
b10 $
b100101100000 #
b100000111010010000101011110010 &
b101001101101100010111111101001 %
#53500
0!
#54000
b0 +
0*
b0 )
0(
b0 $
b0 #
b0 &
b101001101101100010111111101101 %
1'
1!
#54500
0!
#55000
0'
1!
#55100
b110110110101 #
b111000010011101001001110000101 &
b111111011110001110111000011001 %
#55500
0!
#56000
1!
#56100
b111010011110111000011010100111 )
b111010011110110111111010111011 +
1*
1(
b1 $
b11111110000 #
b110001010010001010110110010110 &
b111010011110110111111010110111 %
#56500
0!
#57000
b0 +
0*
b0 )
0(
b0 $
b0 #
b0 &
b111010011110110111111010111011 %
1'
1!
#57500
0!
#58000
0'
1!
#58100
b111100011101001110101010000 )
b10000101110010111001010100101 +
1*
1(
b10 $
b111001001110 #
b111100011101000111100000010 &
b10000101110010111001010100001 %
#58500
0!
#59000
b0 +
0*
b0 )
0(
b0 $
b0 #
b0 &
b10000101110010111001010100101 %
1'
1!
#59500
0!
#60000
0'
1!
#60100
b1111101110110111101000101101 )
b1111101110110110101011110110 +
1*
1(
b1 $
b111100111011 #
b110101100100101011000011111100 &
b1111101110110110101011110010 %
#60500
0!
#61000
b0 +
0*
b0 )
0(
b0 $
b0 #
b0 &
b1111101110110110101011110110 %
1'
1!
#61500
0!
#62000
0'
1!
#62100
b11101100001101111111100001101 )
b100110110001101010011101111000 +
1*
1(
b10 $
b111000000011 #
b11101100001101111000100001010 &
b100110110001101010011101110100 %
#62500
0!
#63000
b0 +
0*
b0 )
0(
b0 $
b0 #
b0 &
b100110110001101010011101111000 %
1'
1!
#63500
0!
#64000
0'
1!
#64100
b111101110110101110011101000100 )
b111101110110101110000100010110 +
1*
1(
b1 $
b11000110010 #
b101110011101011111001010100100 &
b111101110110101110000100010010 %
#64500
0!
#65000
b0 +
0*
b0 )
0(
b0 $
b0 #
b0 &
b111101110110101110000100010110 %
1'
1!
#65500
0!
#66000
0'
1!
#66100
b111101010011010101101111010010 )
b101101101100010000110101010111 +
1*
1(
b10 $
b10010001010 #
b111101010011010101011101001000 &
b101101101100010000110101010011 %
#66500
0!
#67000
b0 +
0*
b0 )
0(
b0 $
b0 #
b0 &
b101101101100010000110101010111 %
1'
1!
#67500
0!
#68000
0'
1!
#68100
b110110010010000110010000110000 )
b110110010010000101110001011010 +
1*
1(
b1 $
b11111011010 #
b100110101010100011011101011000 &
b110110010010000101110001010110 %
#68500
0!
#69000
b0 +
0*
b0 )
0(
b0 $
b0 #
b0 &
b110110010010000101110001011010 %
1'
1!
#69500
0!
#70000
0'
1!
#70100
b100000101000101010110101001111 )
b100000101000101001111000010000 +
1*
1(
b1 $
b111101000011 #
b11110111101110000001011011 &
b100000101000101001111000001100 %
#70500
0!
#71000
b0 +
0*
b0 )
0(
b0 $
b0 #
b0 &
b100000101000101001111000010000 %
1'
1!
#71500
0!
#72000
0'
1!
#72100
b10100110110011101110100010101 )
b10100110110011101000100010101 +
1*
1(
b1 $
b110000000100 #
b10110001001100111000001011101 &
b10100110110011101000100010001 %
#72500
0!
#73000
b0 +
0*
b0 )
0(
b0 $
b0 #
b0 &
b10100110110011101000100010101 %
1'
1!
#73500
0!
#74000
0'
1!
#74100
b10110111000011101000010001101 )
b10110111000011100110001001001 +
1*
1(
b1 $
b10001001000 #
b101101000111100111111001110111 &
b10110111000011100110001000101 %
#74500
0!
#75000
b0 +
0*
b0 )
0(
b0 $
b0 #
b0 &
b10110111000011100110001001001 %
1'
1!
#75500
0!
#76000
0'
1!
#76100
b111110010 #
b11100010111101101110111110110 &
b1101100001110011000100101 %
#76500
0!
#77000
1!
#77100
b11001001 #
b100000011001101100010000111010 &
b1010011000000011111000010011 %
#77500
0!
#78000
1!
#78100
b11011011111111010101000110100 )
b101100000011110111100111101110 +
1*
1(
b10 $
b1110000100 #
b11011011111111010011010110000 &
b101100000011110111100111101010 %
#78500
0!
#79000
b0 +
0*
b0 )
0(
b0 $
b0 #
b0 &
b101100000011110111100111101110 %
1'
1!
#79500
0!
#80000
0'
1!
#80100
b101101100011000110010001100111 )
b101101100011000110000001101011 +
1*
1(
b1 $
b10000000000 #
b100000111011010100100001101110 &
b101101100011000110000001100111 %
#80500
0!
#81000
b0 +
0*
b0 )
0(
b0 $
b0 #
b0 &
b101101100011000110000001101011 %
1'
1!
#81500
0!
#82000
0'
1!
#82100
b10100000001110001101011101110 )
b11110110011001011101111100101 +
1*
1(
b10 $
b100011010000 #
b10100000001110001001000011110 &
b11110110011001011101111100001 %
#82500
0!
#83000
b0 +
0*
b0 )
0(
b0 $
b0 #
b0 &
b11110110011001011101111100101 %
1'
1!
#83500
0!
#84000
0'
1!
#84100
b101100111000001110101000100010 )
b101100111000001101110110001010 +
1*
1(
b1 $
b110010011100 #
b100010111101100001110011000110 &
b101100111000001101110110000110 %
#84500
0!
#85000
b0 +
0*
b0 )
0(
b0 $
b0 #
b0 &
b101100111000001101110110001010 %
1'
1!
#85500
0!
#86000
0'
1!
#86100
b101010000001110001010000001111 )
b101010000001110000111010110001 +
1*
1(
b1 $
b10101100010 #
b11011010010110001100000111000 &
b101010000001110000111010101101 %
#86500
0!
#87000
b0 +
0*
b0 )
0(
b0 $
b0 #
b0 &
b101010000001110000111010110001 %
1'
1!
#87500
0!
#88000
0'
1!
#88100
b110101011000000111010100010001 )
b110101011000000110010100101011 +
1*
1(
b1 $
b111111101010 #
b1000110011101001110010111100 &
b110101011000000110010100100111 %
#88500
0!
#89000
b0 +
0*
b0 )
0(
b0 $
b0 #
b0 &
b110101011000000110010100101011 %
1'
1!
#89500
0!
#90000
0'
1!
#90100
b10100010000100110111110100111 )
b10100011011000101010110110001 +
1*
1(
b10 $
b11001110010 #
b10100010000100110100100110101 &
b10100011011000101010110101101 %
#90500
0!
#91000
b0 +
0*
b0 )
0(
b0 $
b0 #
b0 &
b10100011011000101010110110001 %
1'
1!
#91500
0!
#92000
0'
1!
#92100
b11110011111110111011001001011 )
b11110011111110110110000100000 +
1*
1(
b1 $
b101000101111 #
b101100100101010101111100001110 &
b11110011111110110110000011100 %
#92500
0!
#93000
b0 +
0*
b0 )
0(
b0 $
b0 #
b0 &
b11110011111110110110000100000 %
1'
1!
#93500
0!
#94000
0'
1!
#94100
b1101111100011101011001010001 )
b101010111000111110100000110010 +
1*
1(
b10 $
b110100100 #
b1101111100011101010010101101 &
b101010111000111110100000101110 %
#94500
0!
#95000
b0 +
0*
b0 )
0(
b0 $
b0 #
b0 &
b101010111000111110100000110010 %
1'
1!
#95500
0!
#96000
0'
1!
#96100
b1100001000011111001010 )
b1100000111110000010111 +
1*
1(
b1 $
b101110110111 #
b101101111001111011110111010110 &
b1100000111110000010011 %
#96500
0!
#97000
b0 +
0*
b0 )
0(
b0 $
b0 #
b0 &
b1100000111110000010111 %
1'
1!
#97500
0!
#98000
0'
1!
#98100
b111011001101101111110011010000 )
b111011001101101111100010111001 +
1*
1(
b1 $
b10000011011 #
b111011011110000101011100011110 &
b111011001101101111100010110101 %
#98500
0!
#99000
b0 +
0*
b0 )
0(
b0 $
b0 #
b0 &
b111011001101101111100010111001 %
1'
1!
#99500
0!
#100000
0'
1!
#100100
b10100000001001111101111011000 )
b10100000001001111100110101111 +
1*
1(
b1 $
b1000101101 #
b1001101111010001011000111011 &
b10100000001001111100110101011 %
#100500
0!
#101000
b0 +
0*
b0 )
0(
b0 $
b0 #
b0 &
b10100000001001111100110101111 %
1'
1!
#101500
0!
#102000
0'
1!
#102100
b111011010001000111011011011110 )
b110110011100110001100110000100 +
1*
1(
b10 $
b10101011110 #
b111011010001000111000110000000 &
b110110011100110001100110000000 %
#102500
0!
#103000
b0 +
0*
b0 )
0(
b0 $
b0 #
b0 &
b110110011100110001100110000100 %
1'
1!
#103500
0!
#104000
0'
1!
#104100
b101011110000000010000001000001 )
b101011110000000001001111010100 +
1*
1(
b1 $
b110001110001 #
b100111100110000110000011110 &
b101011110000000001001111010000 %
#104500
0!
#105000
b0 +
0*
b0 )
0(
b0 $
b0 #
b0 &
b101011110000000001001111010100 %
1'
1!
#105500
0!
#106000
0'
1!
#106100
b10000010000101010100011010001 )
b10000010000101010001000001000 +
1*
1(
b1 $
b11011001101 #
b10000000001011110100110100000 &
b10000010000101010001000000100 %
#106500
0!
#107000
b0 +
0*
b0 )
0(
b0 $
b0 #
b0 &
b10000010000101010001000001000 %
1'
1!
#107500
0!
#108000
0'
1!
#108100
b10001111001100100011011000111 )
b10001111001100100010001000111 +
1*
1(
b1 $
b1010000100 #
b110000111100010010111101011100 &
b10001111001100100010001000011 %
#108500
0!
#109000
b0 +
0*
b0 )
0(
b0 $
b0 #
b0 &
b10001111001100100010001000111 %
1'
1!
#109500
0!
#110000
0'
1!
#110100
b101110010010 #
b11011001100011111011011100000 &
b1011011000101111001101000000 %
#110500
0!
#111000
1!
#111100
b100010010010001000100110100011 )
b110011011110110010111111100010 +
1*
1(
b10 $
b11101101101 #
b100010010010001000001000110110 &
b110011011110110010111111011110 %
#111500
0!
#112000
b0 +
0*
b0 )
0(
b0 $
b0 #
b0 &
b110011011110110010111111100010 %
1'
1!
#112500
0!
#113000
0'
1!
#113100
b100111100011010111000011100001 )
b100111100011010110101000001000 +
1*
1(
b1 $
b11011011101 #
b100111100010111000110011011011 &
b100111100011010110101000000100 %
#113500
0!
#114000
b0 +
0*
b0 )
0(
b0 $
b0 #
b0 &
b100111100011010110101000001000 %
1'
1!
#114500
0!
#115000
0'
1!
#115100
b11100010101 #
b111000001001010101111111011101 &
b10110000100011010110000001010 %
#115500
0!
#116000
1!
#116100
b11011011110000001110001000101 )
b11011011110000000110011110100 +
1*
1(
b1 $
b111101010101 #
b11011010000101000100011010001 &
b11011011110000000110011110000 %
#116500
0!
#117000
b0 +
0*
b0 )
0(
b0 $
b0 #
b0 &
b11011011110000000110011110100 %
1'
1!
#117500
0!
#118000
0'
1!
#118100
b100000011011111101001001001000 )
b111010100101100010010000 +
1*
1(
b10 $
b110100101010 #
b100000011011111100010100011110 &
b111010100101100010001100 %
#118500
0!
#119000
b0 +
0*
b0 )
0(
b0 $
b0 #
b0 &
b111010100101100010010000 %
1'
1!
#119500
0!
#120000
0'
1!
#120100
b10000101100100110111110000000 )
b10000101100100110011110010010 +
1*
1(
b1 $
b11111110010 #
b11101010101101111111011110001 &
b10000101100100110011110001110 %
#120500
0!
#121000
b0 +
0*
b0 )
0(
b0 $
b0 #
b0 &
b10000101100100110011110010010 %
1'
1!
#121500
0!
#122000
0'
1!
#122100
b11000111011100101011010010010 )
b101110110010101011100111 +
1*
1(
b10 $
b10000100111 #
b11000111011100101001001101011 &
b101110110010101011100011 %
#122500
0!
#123000
b0 +
0*
b0 )
0(
b0 $
b0 #
b0 &
b101110110010101011100111 %
1'
1!
#123500
0!
#124000
0'
1!
#124100
b11001111010 #
b11010101010001001110000010111 &
b110100010110110001000110100 %
#124500
0!
#125000
1!
#125100
b110101100100 #
b101111010001111010100011101011 &
b110011011001100000011111101010 %
#125500
0!
#126000
1!
#126100
b11101010111 #
b111001101010001101001101000010 &
b111100001111101011011101101111 %
#126500
0!
#127000
1!
#127100
b101101000000000000011000101010 )
b101101000000000000010100000011 +
1*
1(
b1 $
b100101011 #
b110010111010101010001101011010 &
b101101000000000000010011111111 %
#127500
0!
#128000
b0 +
0*
b0 )
0(
b0 $
b0 #
b0 &
b101101000000000000010100000011 %
1'
1!
#128500
0!
#129000
0'
1!
#129100
b100111000001111111000100001011 )
b110101001111000010110011001 +
1*
1(
b10 $
b100010101 #
b100111000001111110111111110110 &
b110101001111000010110010101 %
#129500
0!
#130000
b0 +
0*
b0 )
0(
b0 $
b0 #
b0 &
b110101001111000010110011001 %
1'
1!
#130500
0!
#131000
0'
1!
#131100
b1111101101101110100111000101 )
b11011011101001111100101001100 +
1*
1(
b10 $
b100001101001 #
b1111101101101110000101011100 &
b11011011101001111100101001000 %
#131500
0!
#132000
b0 +
0*
b0 )
0(
b0 $
b0 #
b0 &
b11011011101001111100101001100 %
1'
1!
#132500
0!
#133000
0'
1!
#133100
b110110001100110100110001100101 )
b10000010101001011001100110011 +
1*
1(
b10 $
b111111100001 #
b110110001100110011110010000100 &
b10000010101001011001100101111 %
#133500
0!
#134000
b0 +
0*
b0 )
0(
b0 $
b0 #
b0 &
b10000010101001011001100110011 %
1'
1!
#134500
0!
#135000
0'
1!
#135100
b11000011100 #
b1001110010000100000000001110 &
b11011110111001000110110000101 %
#135500
0!
#136000
1!
#136100
b10001001 #
b1111000011111001001111010000 &
b11101000101100011111100110 %
#136500
0!
#137000
1!
#137100
b11001011111010001000001000011 )
b101110000000110100010011000111 +
1*
1(
b10 $
b11111000000 #
b11001011111010000100010000011 &
b101110000000110100010011000011 %
#137500
0!
#138000
b0 +
0*
b0 )
0(
b0 $
b0 #
b0 &
b101110000000110100010011000111 %
1'
1!
#138500
0!
#139000
0'
1!
#139100
b110111110011 #
b100111100100111101110001 &
b111111110001001111100101000001 %
#139500
0!
#140000
1!
#140100
b101010101001100011010001001000 )
b101010101001100011000110101011 +
1*
1(
b1 $
b1010100001 #
b100111010110001101001110000 &
b101010101001100011000110100111 %
#140500
0!
#141000
b0 +
0*
b0 )
0(
b0 $
b0 #
b0 &
b101010101001100011000110101011 %
1'
1!
#141500
0!
#142000
0'
1!
#142100
b1111111001111101010101010001 )
b1100010100001010010101010000 +
1*
1(
b10 $
b10011100000 #
b1111111001111101000001110001 &
b1100010100001010010101001100 %
#142500
0!
#143000
b0 +
0*
b0 )
0(
b0 $
b0 #
b0 &
b1100010100001010010101010000 %
1'
1!
#143500
0!
#144000
0'
1!
#144100
b10101100100001101010001001000 )
b10101100100001100110000111010 +
1*
1(
b1 $
b100000010010 #
b110100001110100101111100011101 &
b10101100100001100110000110110 %
#144500
0!
#145000
b0 +
0*
b0 )
0(
b0 $
b0 #
b0 &
b10101100100001100110000111010 %
1'
1!
#145500
0!
#146000
0'
1!
#146100
b1101001000111001010101001110 )
b1101001000111001001101110011 +
1*
1(
b1 $
b111011111 #
b1001110111111011001011011100 &
b1101001000111001001101101111 %
#146500
0!
#147000
b0 +
0*
b0 )
0(
b0 $
b0 #
b0 &
b1101001000111001001101110011 %
1'
1!
#147500
0!
#148000
0'
1!
#148100
b110100010000100000010000000000 )
b110100010000100000001000001000 +
1*
1(
b1 $
b111111100 #
b101100010111010010011010001000 &
b110100010000100000001000000100 %
#148500
0!
#149000
b0 +
0*
b0 )
0(
b0 $
b0 #
b0 &
b110100010000100000001000001000 %
1'
1!
#149500
0!
#150000
0'
1!
#150100
b100001111101101110000000111100 )
b100011000100010000101101000000 +
1*
1(
b10 $
b111001011010 #
b100001111101101101000111100010 &
b100011000100010000101100111100 %
#150500
0!
#151000
b0 +
0*
b0 )
0(
b0 $
b0 #
b0 &
b100011000100010000101101000000 %
1'
1!
#151500
0!
#152000
0'
1!
#152100
b1010010000101010011101100010 )
b1010010000101001110001100111 +
1*
1(
b1 $
b101011111111 #
b11011101111001001100001011111 &
b1010010000101001110001100011 %
#152500
0!
#153000
b0 +
0*
b0 )
0(
b0 $
b0 #
b0 &
b1010010000101001110001100111 %
1'
1!
#153500
0!
#154000
0'
1!
#154100
b111111011111010000001111010010 )
b110000000010000110011010111001 +
1*
1(
b10 $
b1100010 #
b111111011111010000001101110000 &
b110000000010000110011010110101 %
#154500
0!
#155000
b0 +
0*
b0 )
0(
b0 $
b0 #
b0 &
b110000000010000110011010111001 %
1'
1!
#155500
0!
#156000
0'
1!
#156100
b101110101000011011000101100 )
b101110101000010011101000001 +
1*
1(
b1 $
b111011101111 #
b111010100110101010100111010110 &
b101110101000010011100111101 %
#156500
0!
#157000
b0 +
0*
b0 )
0(
b0 $
b0 #
b0 &
b101110101000010011101000001 %
1'
1!
#157500
0!
#158000
0'
1!
#158100
b10111110111 #
b11010101101110010011100100 &
b10001101100110011001010111001 %
#158500
0!
#159000
1!
#159100
b1011100011110111011101000101 )
b101110011000110100111 +
1*
1(
b10 $
b11011111 #
b1011100011110111011001100110 &
b101110011000110100011 %
#159500
0!
#160000
b0 +
0*
b0 )
0(
b0 $
b0 #
b0 &
b101110011000110100111 %
1'
1!
#160500
0!
#161000
0'
1!
#161100
b111111001111111000101111000010 )
b100011100111100110111100010101 +
1*
1(
b10 $
b1001011001 #
b111111001111111000100101101001 &
b100011100111100110111100010001 %
#161500
0!
#162000
b0 +
0*
b0 )
0(
b0 $
b0 #
b0 &
b100011100111100110111100010101 %
1'
1!
#162500
0!
#163000
0'
1!
#163100
b10011001001 #
b10001111110111011000001011011 &
b111011011010011110110010000 %
#163500
0!
#164000
1!
#164100
b10001111001000110010001011101 )
b10001111001000101101011011111 +
1*
1(
b1 $
b100110000010 #
b110001100011101000001010001100 &
b10001111001000101101011011011 %
#164500
0!
#165000
b0 +
0*
b0 )
0(
b0 $
b0 #
b0 &
b10001111001000101101011011111 %
1'
1!
#165500
0!
#166000
0'
1!
#166100
b1001011 #
b1111001000100001010010101000 &
b100011000001100001010000010111 %
#166500
0!
#167000
1!
#167100
b1011111001 #
b10000101001111111000101000011 &
b110100010010011110100111011010 %
#167500
0!
#168000
1!
#168100
b100111100111110000101001100111 )
b100111100111110000001011001110 +
1*
1(
b1 $
b11110011101 #
b111101000000001010111110011110 &
b100111100111110000001011001010 %
#168500
0!
#169000
b0 +
0*
b0 )
0(
b0 $
b0 #
b0 &
b100111100111110000001011001110 %
1'
1!
#169500
0!
#170000
0'
1!
#170100
b110101110100 #
b11101011100010111010111110010 &
b10011010101110010000000100 %
#170500
0!
#171000
1!
#171100
b101000001101 #
b111011001110110010111000101010 &
b101000111110010001001010010100 %
