load.sv
`ifndef FILE_INCL
    `include "processor_defines.sv"
`endif

module load(
    input logic i_clk,
    input logic i_rst,
    input logic [31:0] rs1_val,
    input logic [31:0] imm,
    input logic [31:0] mem_data,
    input logic [4:0] rd_in,
    input logic [2:0] load_control,
    output logic stall_pc,
    output logic ignore_curr_inst,
    output logic rd_write_control,
    output logic [4:0] rd_out,
    output logic [31:0] rd_write_val,
    output logic mem_rw_mode,
    output logic [31:0] mem_addr
);
    parameter RESET_STATE = 0;
    parameter READ_MEM=1;
    logic state;
    logic next_state;
    logic [2:0] load_control_s;
    logic [4:0] rd_s;
    logic [31:0]mem_addr_s;

    assign mem_rw_mode =1'b1;

    always@(posedge i_clk or negedge i_rst) begin

        if(~i_rst) begin
            state <= 'b0;
            load_control_s<= 'b0;
            rd_s <= 'b0;
            mem_addr_s<='b0;
        end
        else begin
            load_control_s<= load_control;
            rd_s <= rd_in;
            state <= next_state; 
            mem_addr_s<= mem_addr;
        end

    end

    always@(*) begin
            case(state) 
            RESET_STATE: begin
                ignore_curr_inst='b0;
                rd_write_control='b0;
                rd_write_val='b0;
                rd_out='b0;
                if(|load_control) begin
                    mem_addr= imm+ rs1_val;
                    stall_pc='b1; 
                    next_state = READ_MEM;
                    end
                else begin
                next_state = RESET_STATE;
                stall_pc='b0;
                mem_addr='b0;
                ignore_curr_inst='b0;
                rd_write_control='b0;
                rd_write_val='b0;
                end
            end
            

            READ_MEM: begin
                case(load_control_s)

                `LD_NOP: begin 
                    rd_write_control='b0;
                    rd_write_val='b0; end

                `LB: begin
                    rd_write_control=1'b1;
                    if(mem_addr_s[1:0]==2'b00)
                    rd_write_val= {{24{mem_data[7]}},mem_data[7:0]};
                    else if(mem_addr_s[1:0]==2'b01)
                    rd_write_val= {{24{mem_data[15]}},mem_data[15:8]};
                    else if(mem_addr_s[1:0]==2'b10)
                    rd_write_val= {{24{mem_data[23]}},mem_data[23:16]};
                    else
                    rd_write_val= {{24{mem_data[31]}},mem_data[31:24]};
                     end

                `LH:begin
                    rd_write_control='b1;
                    if(mem_addr_s[1]==0)
                    rd_write_val= {{16{mem_data[15]}},mem_data[15:0]};
                    else 
                    rd_write_val= {{16{mem_data[31]}},mem_data[31:16]};
                    end

                `LW:begin
                    rd_write_val = mem_data;
                    rd_write_control=1'b1;
                    end
                    
                `LBU:begin
                    rd_write_control=1'b1;
                    if(mem_addr_s[1:0]==2'b00)
                    rd_write_val= {24'b0,mem_data[7:0]};
                    else if(mem_addr_s[1:0]==2'b01)
                    rd_write_val= {24'b0,mem_data[15:8]};
                    else if(mem_addr_s[1:0]==2'b10)
                    rd_write_val= {24'b0,mem_data[23:16]};
                    else
                    rd_write_val= {24'b0,mem_data[31:24]};
                     end
                `LHU:begin
                    rd_write_control=1'b1;
                    if(mem_addr_s[1]==0)
                    rd_write_val= {16'b0,mem_data[15:0]};
                    else 
                    rd_write_val= {16'b0,mem_data[31:16]};
                     end
                endcase

                stall_pc=1'b0;
                ignore_curr_inst='b1;
                rd_out= rd_s;
                next_state = RESET_STATE;
                mem_addr='b0;
            end

            endcase
    end

`ifndef SUBMODULE_DISABLE_WAVES
   initial
     begin
        $dumpfile("./sim_build/load.vcd");
        $dumpvars(0, load);
     end
 `endif

endmodule

load.vcd
$date
	Tue Jul  2 12:25:52 2024
$end
$version
	Icarus Verilog
$end
$timescale
	1ps
$end
$scope module load $end
$var wire 1 ! i_clk $end
$var wire 1 " i_rst $end
$var wire 32 # imm [31:0] $end
$var wire 3 $ load_control [2:0] $end
$var wire 32 % mem_data [31:0] $end
$var wire 1 & mem_rw_mode $end
$var wire 5 ' rd_in [4:0] $end
$var wire 32 ( rs1_val [31:0] $end
$var parameter 32 ) READ_MEM $end
$var parameter 32 * RESET_STATE $end
$var reg 1 + ignore_curr_inst $end
$var reg 3 , load_control_s [2:0] $end
$var reg 32 - mem_addr [31:0] $end
$var reg 32 . mem_addr_s [31:0] $end
$var reg 1 / next_state $end
$var reg 5 0 rd_out [4:0] $end
$var reg 5 1 rd_s [4:0] $end
$var reg 1 2 rd_write_control $end
$var reg 32 3 rd_write_val [31:0] $end
$var reg 1 4 stall_pc $end
$var reg 1 5 state $end
$upscope $end
$enddefinitions $end
$comment Show the parameter values. $end
$dumpall
b0 *
b1 )
$end
#0
$dumpvars
x5
x4
bx 3
x2
bx 1
bx 0
x/
bx .
bx -
bx ,
x+
b0 (
b0 '
1&
b0 %
b0 $
b0 #
1"
0!
$end
#5000
b0 1
b0 ,
1!
#5500
b0 -
04
0/
b0 0
b0 3
02
0+
b0 .
05
0"
0!
#6000
1!
#6500
0!
#7000
1"
1!
#7500
0!
#8000
1!
#8100
1/
14
b1011110011011010011101000000 -
b1 $
b11 '
b100110010000 #
b1011110011011001110110110000 (
#8500
0!
#9000
b1010111 3
b0 #
b0 (
b0 '
b0 $
b1111001110010101001100101010111 %
b0 -
0/
b11 0
1+
04
12
b1011110011011010011101000000 .
15
b11 1
b1 ,
1!
#9500
0!
#10000
b0 0
b0 3
02
0+
b0 .
05
b0 1
b0 ,
1!
#10100
1/
14
b110000101011100101100001100011 -
b1 $
b10000 '
b0 %
b100110000 #
b110000101011100101011100110011 (
#10500
0!
#11000
b11111111111111111111111110011000 3
b0 #
b0 (
b0 '
b0 $
b10011000101010010001001000100100 %
b0 -
0/
b10000 0
1+
04
12
b110000101011100101100001100011 .
15
b10000 1
b1 ,
1!
#11500
0!
#12000
b0 0
b0 3
02
0+
b0 .
05
b0 1
b0 ,
1!
#12100
1/
14
b101100011111111111101000100010 -
b11 $
b10111 '
b0 %
b11100011001 #
b101100011111111111001100001001 (
#12500
0!
#13000
b11100001011010100100110110010 3
b0 #
b0 (
b0 '
b0 $
b11100001011010100100110110010 %
b0 -
0/
b10111 0
1+
04
12
b101100011111111111101000100010 .
15
b10111 1
b11 ,
1!
#13500
0!
#14000
b0 0
b0 3
02
0+
b0 .
05
b0 1
b0 ,
1!
#14100
1/
14
b10101001101001100001001010111 -
b10 $
b10011 '
b0 %
b110111000 #
b10101001101001100000010011111 (
#14500
0!
#15000
b101000001011110 3
b0 #
b0 (
b0 '
b0 $
b1010000010111101101101100110100 %
b0 -
0/
b10011 0
1+
04
12
b10101001101001100001001010111 .
15
b10011 1
b10 ,
1!
#15500
0!
#16000
b0 0
b0 3
02
0+
b0 .
05
b0 1
b0 ,
1!
#16100
1/
14
b10000111000110110000111111011 -
b11 $
b10110 '
b0 %
b1000000110 #
b10000111000110101111111110101 (
#16500
0!
#17000
b1100000001100110101011111001101 3
b0 #
b0 (
b0 '
b0 $
b1100000001100110101011111001101 %
b0 -
0/
b10110 0
1+
04
12
b10000111000110110000111111011 .
15
b10110 1
b11 ,
1!
#17500
0!
#18000
b0 0
b0 3
02
0+
b0 .
05
b0 1
b0 ,
1!
#18100
b11 '
b0 %
b11110110011 #
b111101100101010001000000111 (
#18500
0!
#19000
b11 1
1!
#19100
1/
14
b11100111111011111100111010001 -
b101 $
b1010 '
b101011110100 #
b11100111111011110111011011101 (
#19500
0!
#20000
b1011101110101001 3
b0 #
b0 (
b0 '
b0 $
b1000110010110101011101110101001 %
b0 -
0/
b1010 0
1+
04
12
b11100111111011111100111010001 .
15
b1010 1
b101 ,
1!
#20500
0!
#21000
b0 0
b0 3
02
0+
b0 .
05
b0 1
b0 ,
1!
#21100
1/
14
b101111010110010110001001010010 -
b100 $
b100 '
b0 %
b1101110000 #
b101111010110010101111011100010 (
#21500
0!
#22000
b11101 3
b0 #
b0 (
b0 '
b0 $
b1101001000111011111010000010010 %
b0 -
0/
b100 0
1+
04
12
b101111010110010110001001010010 .
15
b100 1
b100 ,
1!
#22500
0!
#23000
b0 0
b0 3
02
0+
b0 .
05
b0 1
b0 ,
1!
#23100
1/
14
b10100001000000011000100111 -
b11 $
b10111 '
b0 %
b1101000011 #
b10100001000000001011100100 (
#23500
0!
#24000
b11110010110001001010110100010101 3
b0 #
b0 (
b0 '
b0 $
b11110010110001001010110100010101 %
b0 -
0/
b10111 0
1+
04
12
b10100001000000011000100111 .
15
b10111 1
b11 ,
1!
#24500
0!
#25000
b0 0
b0 3
02
0+
b0 .
05
b0 1
b0 ,
1!
#25100
1/
14
b110000011101010010010010111001 -
b1 $
b1110 '
b0 %
b10000000 #
b110000011101010010010000111001 (
#25500
0!
#26000
b1001 3
b0 #
b0 (
b0 '
b0 $
b10011001011110010000100111000111 %
b0 -
0/
b1110 0
1+
04
12
b110000011101010010010010111001 .
15
b1110 1
b1 ,
1!
#26500
0!
#27000
b0 0
b0 3
02
0+
b0 .
05
b0 1
b0 ,
1!
#27100
1/
14
b101001010011000110001100111001 -
b1 $
b11011 '
b0 %
b11111000001 #
b101001010011000101101101111000 (
#27500
0!
#28000
b100 3
b0 #
b0 (
b0 '
b0 $
b10110011011100100000010010110001 %
b0 -
0/
b11011 0
1+
04
12
b101001010011000110001100111001 .
15
b11011 1
b1 ,
1!
#28500
0!
#29000
b0 0
b0 3
02
0+
b0 .
05
b0 1
b0 ,
1!
#29100
1/
14
b100101001010101100100110011011 -
b11 $
b10000 '
b0 %
b11110001111 #
b100101001010101100001000001100 (
#29500
0!
#30000
b11101110100001110110110111111011 3
b0 #
b0 (
b0 '
b0 $
b11101110100001110110110111111011 %
b0 -
0/
b10000 0
1+
04
12
b100101001010101100100110011011 .
15
b10000 1
b11 ,
1!
#30500
0!
#31000
b0 0
b0 3
02
0+
b0 .
05
b0 1
b0 ,
1!
#31100
1/
14
b111000000111010011001100011100 -
b10 $
b101 '
b0 %
b11101001101 #
b111000000111010010101111001111 (
#31500
0!
#32000
b101110001100011 3
b0 #
b0 (
b0 '
b0 $
b1110010011000101110001100011 %
b0 -
0/
b101 0
1+
04
12
b111000000111010011001100011100 .
15
b101 1
b10 ,
1!
#32500
0!
#33000
b0 0
b0 3
02
0+
b0 .
05
b0 1
b0 ,
1!
#33100
b10101 '
b0 %
b11010011100 #
b1100010100011011011001001000 (
#33500
0!
#34000
b10101 1
1!
#34100
1/
14
b11111001110110101101110011111 -
b11 $
b1111 '
b10001100101 #
b11111001110110101011100111010 (
#34500
0!
#35000
b11011000001001011010001011101011 3
b0 #
b0 (
b0 '
b0 $
b11011000001001011010001011101011 %
b0 -
0/
b1111 0
1+
04
12
b11111001110110101101110011111 .
15
b1111 1
b11 ,
1!
#35500
0!
#36000
b0 0
b0 3
02
0+
b0 .
05
b0 1
b0 ,
1!
#36100
1/
14
b10000001001000111001001011011 -
b100 $
b11 '
b0 %
b11100010010 #
b10000001001000110101101001001 (
#36500
0!
#37000
b110101 3
b0 #
b0 (
b0 '
b0 $
b110101010000111101011001111010 %
b0 -
0/
b11 0
1+
04
12
b10000001001000111001001011011 .
15
b11 1
b100 ,
1!
#37500
0!
#38000
b0 0
b0 3
02
0+
b0 .
05
b0 1
b0 ,
1!
#38100
1/
14
b10111000001011101111100111100 -
b1 $
b1 '
b0 %
b100100001010 #
b10111000001011101011000110010 (
#38500
0!
#39000
b11111111111111111111111111010110 3
b0 #
b0 (
b0 '
b0 $
b101111011011011001010111010110 %
b0 -
0/
b1 0
1+
04
12
b10111000001011101111100111100 .
15
b1 1
b1 ,
1!
#39500
0!
#40000
b0 0
b0 3
02
0+
b0 .
05
b0 1
b0 ,
1!
#40100
1/
14
b10010001011100011011000101011 -
b1 $
b10111 '
b0 %
b11000000101 #
b10010001011100011000000100110 (
#40500
0!
#41000
b11111111111111111111111110001011 3
b0 #
b0 (
b0 '
b0 $
b10001011111011010001010111101100 %
b0 -
0/
b10111 0
1+
04
12
b10010001011100011011000101011 .
15
b10111 1
b1 ,
1!
#41500
0!
#42000
b0 0
b0 3
02
0+
b0 .
05
b0 1
b0 ,
1!
#42100
b101 '
b0 %
b110111111 #
b11000000100100111101110111111 (
#42500
0!
#43000
b101 1
1!
#43100
1/
14
b10111110100000001101011111011 -
b101 $
b10100 '
b1000111100 #
b10111110100000001100010111111 (
#43500
0!
#44000
b1101011000111100 3
b0 #
b0 (
b0 '
b0 $
b11010110001111000000000011011010 %
b0 -
0/
b10100 0
1+
04
12
b10111110100000001101011111011 .
15
b10100 1
b101 ,
1!
#44500
0!
#45000
b0 0
b0 3
02
0+
b0 .
05
b0 1
b0 ,
1!
#45100
1/
14
b1011001010100111111010101101 -
b100 $
b10110 '
b0 %
b101110000111 #
b1011001010100111001100100110 (
#45500
0!
#46000
b110001 3
b0 #
b0 (
b0 '
b0 $
b11101110101101000011000101000000 %
b0 -
0/
b10110 0
1+
04
12
b1011001010100111111010101101 .
15
b10110 1
b100 ,
1!
#46500
0!
#47000
b0 0
b0 3
02
0+
b0 .
05
b0 1
b0 ,
1!
#47100
1/
14
b101011000011000000111111010110 -
b101 $
b11001 '
b0 %
b100011001101 #
b101011000011000000011100001001 (
#47500
0!
#48000
b100101100101111 3
b0 #
b0 (
b0 '
b0 $
b1001011001011110101110110001111 %
b0 -
0/
b11001 0
1+
04
12
b101011000011000000111111010110 .
15
b11001 1
b101 ,
1!
#48500
0!
#49000
b0 0
b0 3
02
0+
b0 .
05
b0 1
b0 ,
1!
#49100
1/
14
b101111001001101111001100111111 -
b1 $
b11001 '
b0 %
b101111100 #
b101111001001101111000111000011 (
#49500
0!
#50000
b1100110 3
b0 #
b0 (
b0 '
b0 $
b1100110011010101000010010101001 %
b0 -
0/
b11001 0
1+
04
12
b101111001001101111001100111111 .
15
b11001 1
b1 ,
1!
#50500
0!
#51000
b0 0
b0 3
02
0+
b0 .
05
b0 1
b0 ,
1!
#51100
1/
14
b111100001110111111101111101011 -
b100 $
b10000 '
b0 %
b100011001000 #
b111100001110111111001100100011 (
#51500
0!
#52000
b11111100 3
b0 #
b0 (
b0 '
b0 $
b11111100100100101011100100111110 %
b0 -
0/
b10000 0
1+
04
12
b111100001110111111101111101011 .
15
b10000 1
b100 ,
1!
#52500
0!
#53000
b0 0
b0 3
02
0+
b0 .
05
b0 1
b0 ,
1!
#53100
b1011 '
b0 %
b101010001110 #
b111101000100011110000010000111 (
#53500
0!
#54000
b1011 1
1!
#54100
1/
14
b110011001100001010010111011101 -
b101 $
b10011 '
b110001001001 #
b110011001100001001100110010100 (
#54500
0!
#55000
b1001111010010110 3
b0 #
b0 (
b0 '
b0 $
b11001000011111111001111010010110 %
b0 -
0/
b10011 0
1+
04
12
b110011001100001010010111011101 .
15
b10011 1
b101 ,
1!
#55500
0!
#56000
b0 0
b0 3
02
0+
b0 .
05
b0 1
b0 ,
1!
#56100
1/
14
b110000101001011000111111111111 -
b10 $
b1111 '
b0 %
b11110111000 #
b110000101001011000100001000111 (
#56500
0!
#57000
b100100001011001 3
b0 #
b0 (
b0 '
b0 $
b1001000010110010111011001001011 %
b0 -
0/
b1111 0
1+
04
12
b110000101001011000111111111111 .
15
b1111 1
b10 ,
1!
#57500
0!
#58000
b0 0
b0 3
02
0+
b0 .
05
b0 1
b0 ,
1!
#58100
1/
14
b110001110110011100010100011000 -
b11 $
b1010 '
b0 %
b100011010011 #
b110001110110011011110001000101 (
#58500
0!
#59000
b1100011110010010100010111001101 3
b0 #
b0 (
b0 '
b0 $
b1100011110010010100010111001101 %
b0 -
0/
b1010 0
1+
04
12
b110001110110011100010100011000 .
15
b1010 1
b11 ,
1!
#59500
0!
#60000
b0 0
b0 3
02
0+
b0 .
05
b0 1
b0 ,
1!
#60100
1/
14
b1001101100100000101111111110 -
b10 $
b10001 '
b0 %
b1000000011 #
b1001101100100000100111111011 (
#60500
0!
#61000
b110001100100111 3
b0 #
b0 (
b0 '
b0 $
b1100011001001111111001100011001 %
b0 -
0/
b10001 0
1+
04
12
b1001101100100000101111111110 .
15
b10001 1
b10 ,
1!
#61500
0!
#62000
b0 0
b0 3
02
0+
b0 .
05
b0 1
b0 ,
1!
#62100
b11001 '
b0 %
b101101110110 #
b100010010100010000011101111100 (
#62500
0!
#63000
b11001 1
1!
#63100
1/
14
b11100001110010010100111101100 -
b10 $
b1110 '
b111101010001 #
b11100001110010001101010011011 (
#63500
0!
#64000
b11111111111111111000010010101100 3
b0 #
b0 (
b0 '
b0 $
b11110000101011111000010010101100 %
b0 -
0/
b1110 0
1+
04
12
b11100001110010010100111101100 .
15
b1110 1
b10 ,
1!
#64500
0!
#65000
b0 0
b0 3
02
0+
b0 .
05
b0 1
b0 ,
1!
#65100
1/
14
b1010000101110010010011011011 -
b10 $
b10010 '
b0 %
b11001010000 #
b1010000101110001111010001011 (
#65500
0!
#66000
b11111111111111111011100010000110 3
b0 #
b0 (
b0 '
b0 $
b10111000100001100000111101110111 %
b0 -
0/
b10010 0
1+
04
12
b1010000101110010010011011011 .
15
b10010 1
b10 ,
1!
#66500
0!
#67000
b0 0
b0 3
02
0+
b0 .
05
b0 1
b0 ,
1!
#67100
1/
14
b111000100010001001111010000111 -
b10 $
b1010 '
b0 %
b11010100111 #
b111000100010001001011111100000 (
#67500
0!
#68000
b100100000011110 3
b0 #
b0 (
b0 '
b0 $
b1001000000111101000010001011001 %
b0 -
0/
b1010 0
1+
04
12
b111000100010001001111010000111 .
15
b1010 1
b10 ,
1!
#68500
0!
#69000
b0 0
b0 3
02
0+
b0 .
05
b0 1
b0 ,
1!
#69100
1/
14
b100000001101110010010000110000 -
b101 $
b1111 '
b0 %
b101011010 #
b100000001101110010001011010110 (
#69500
0!
#70000
b101101010100 3
b0 #
b0 (
b0 '
b0 $
b110000111100000101101010100 %
b0 -
0/
b1111 0
1+
04
12
b100000001101110010010000110000 .
15
b1111 1
b101 ,
1!
#70500
0!
#71000
b0 0
b0 3
02
0+
b0 .
05
b0 1
b0 ,
1!
#71100
1/
14
b11110001001110101010011101010 -
b100 $
b11110 '
b0 %
b101100001011 #
b11110001001110100100111011111 (
#71500
0!
#72000
b10001110 3
b0 #
b0 (
b0 '
b0 $
b11101101100011100101101100111100 %
b0 -
0/
b11110 0
1+
04
12
b11110001001110101010011101010 .
15
b11110 1
b100 ,
1!
#72500
0!
#73000
b0 0
b0 3
02
0+
b0 .
05
b0 1
b0 ,
1!
#73100
1/
14
b110010000101110011010101000001 -
b11 $
b1001 '
b0 %
b1010111101 #
b110010000101110011001010000100 (
#73500
0!
#74000
b110100111010000001010001111000 3
b0 #
b0 (
b0 '
b0 $
b110100111010000001010001111000 %
b0 -
0/
b1001 0
1+
04
12
b110010000101110011010101000001 .
15
b1001 1
b11 ,
1!
#74500
0!
#75000
b0 0
b0 3
02
0+
b0 .
05
b0 1
b0 ,
1!
#75100
1/
14
b100011010001111000011101011101 -
b1 $
b10011 '
b0 %
b101110111001 #
b100011010001110111101110100100 (
#75500
0!
#76000
b11111111111111111111111110101110 3
b0 #
b0 (
b0 '
b0 $
b11101001011101001010111011111110 %
b0 -
0/
b10011 0
1+
04
12
b100011010001111000011101011101 .
15
b10011 1
b1 ,
1!
#76500
0!
#77000
b0 0
b0 3
02
0+
b0 .
05
b0 1
b0 ,
1!
#77100
1/
14
b101001001010101111101010111001 -
b10 $
b1000 '
b0 %
b10010001101 #
b101001001010101111011000101100 (
#77500
0!
#78000
b11111111111111111101001101001101 3
b0 #
b0 (
b0 '
b0 $
b1010010101010101101001101001101 %
b0 -
0/
b1000 0
1+
04
12
b101001001010101111101010111001 .
15
b1000 1
b10 ,
1!
#78500
0!
#79000
b0 0
b0 3
02
0+
b0 .
05
b0 1
b0 ,
1!
#79100
1/
14
b1001010101101110000 -
b1 $
b1010 '
b0 %
b100011001011 #
b1001010001010100101 (
#79500
0!
#80000
b11111111111111111111111111110001 3
b0 #
b0 (
b0 '
b0 $
b10010010010001010000001111110001 %
b0 -
0/
b1010 0
1+
04
12
b1001010101101110000 .
15
b1010 1
b1 ,
1!
#80500
0!
#81000
b0 0
b0 3
02
0+
b0 .
05
b0 1
b0 ,
1!
#81100
1/
14
b11011010001101111101101000101 -
b101 $
b1000 '
b0 %
b101010110110 #
b11011010001101111000010001111 (
#81500
0!
#82000
b1000101001001111 3
b0 #
b0 (
b0 '
b0 $
b1001001110100111000101001001111 %
b0 -
0/
b1000 0
1+
04
12
b11011010001101111101101000101 .
15
b1000 1
b101 ,
1!
#82500
0!
#83000
b0 0
b0 3
02
0+
b0 .
05
b0 1
b0 ,
1!
#83100
b1111 '
b0 %
b101011011100 #
b1011100101111101111110111001 (
#83500
0!
#84000
b1111 1
1!
#84100
1/
14
b111100101011110100001011101111 -
b11 $
b110 '
b1000100000 #
b111100101011110100000011001111 (
#84500
0!
#85000
b10000111011111110011000001000101 3
b0 #
b0 (
b0 '
b0 $
b10000111011111110011000001000101 %
b0 -
0/
b110 0
1+
04
12
b111100101011110100001011101111 .
15
b110 1
b11 ,
1!
#85500
0!
#86000
b0 0
b0 3
02
0+
b0 .
05
b0 1
b0 ,
1!
#86100
1/
14
b10001000000111011000001111101 -
b100 $
b1101 '
b0 %
b111010100011 #
b10001000000111010000111011010 (
#86500
0!
#87000
b111101 3
b0 #
b0 (
b0 '
b0 $
b10011100010100100011110101010110 %
b0 -
0/
b1101 0
1+
04
12
b10001000000111011000001111101 .
15
b1101 1
b100 ,
1!
#87500
0!
#88000
b0 0
b0 3
02
0+
b0 .
05
b0 1
b0 ,
1!
#88100
1/
14
b111000011101110100110100010110 -
b1 $
b11001 '
b0 %
b10101010110 #
b111000011101110100011111000000 (
#88500
0!
#89000
b111101 3
b0 #
b0 (
b0 '
b0 $
b11110011001111010011111011010101 %
b0 -
0/
b11001 0
1+
04
12
b111000011101110100110100010110 .
15
b11001 1
b1 ,
1!
#89500
0!
#90000
b0 0
b0 3
02
0+
b0 .
05
b0 1
b0 ,
1!
#90100
1/
14
b100011110001110110001100010110 -
b10 $
b100 '
b0 %
b101111100011 #
b100011110001110101011100110011 (
#90500
0!
#91000
b110100101010111 3
b0 #
b0 (
b0 '
b0 $
b1101001010101111111100101110010 %
b0 -
0/
b100 0
1+
04
12
b100011110001110110001100010110 .
15
b100 1
b10 ,
1!
#91500
0!
#92000
b0 0
b0 3
02
0+
b0 .
05
b0 1
b0 ,
1!
#92100
1/
14
b1010100100010101100111111000 -
b1 $
b11010 '
b0 %
b111011011011 #
b1010100100010100101100011101 (
#92500
0!
#93000
b11111111111111111111111111011110 3
b0 #
b0 (
b0 '
b0 $
b10111010101001111100011111011110 %
b0 -
0/
b11010 0
1+
04
12
b1010100100010101100111111000 .
15
b11010 1
b1 ,
1!
#93500
0!
#94000
b0 0
b0 3
02
0+
b0 .
05
b0 1
b0 ,
1!
#94100
1/
14
b110101010001010111101110010101 -
b11 $
b1010 '
b0 %
b11101110111 #
b110101010001010111010000011110 (
#94500
0!
#95000
b1101110111010100110110010101001 3
b0 #
b0 (
b0 '
b0 $
b1101110111010100110110010101001 %
b0 -
0/
b1010 0
1+
04
12
b110101010001010111101110010101 .
15
b1010 1
b11 ,
1!
#95500
0!
#96000
b0 0
b0 3
02
0+
b0 .
05
b0 1
b0 ,
1!
#96100
1/
14
b1010111110011001011000000 -
b101 $
b100 '
b0 %
b10111011110 #
b1010111110010110011100010 (
#96500
0!
#97000
b111011010111011 3
b0 #
b0 (
b0 '
b0 $
b10010001010110111011010111011 %
b0 -
0/
b100 0
1+
04
12
b1010111110011001011000000 .
15
b100 1
b101 ,
1!
#97500
0!
#98000
b0 0
b0 3
02
0+
b0 .
05
b0 1
b0 ,
1!
#98100
1/
14
b101101101010000001000101011110 -
b11 $
b1110 '
b0 %
b101011101 #
b101101101010000001000000000001 (
#98500
0!
#99000
b101011001010110011101010010101 3
b0 #
b0 (
b0 '
b0 $
b101011001010110011101010010101 %
b0 -
0/
b1110 0
1+
04
12
b101101101010000001000101011110 .
15
b1110 1
b11 ,
1!
#99500
0!
#100000
b0 0
b0 3
02
0+
b0 .
05
b0 1
b0 ,
1!
#100100
1/
14
b110100000011001010011011111111 -
b10 $
b11111 '
b0 %
b110011110000 #
b110100000011001001101000001111 (
#100500
0!
#101000
b11111111111111111110100000001010 3
b0 #
b0 (
b0 '
b0 $
b11101000000010100111010111011010 %
b0 -
0/
b11111 0
1+
04
12
b110100000011001010011011111111 .
15
b11111 1
b10 ,
1!
#101500
0!
#102000
b0 0
b0 3
02
0+
b0 .
05
b0 1
b0 ,
1!
#102100
1/
14
b101001000001101001101101001 -
b11 $
b1001 '
b0 %
b1000100101 #
b101001000001101000101000100 (
#102500
0!
#103000
b1000100001100011011111010000101 3
b0 #
b0 (
b0 '
b0 $
b1000100001100011011111010000101 %
b0 -
0/
b1001 0
1+
04
12
b101001000001101001101101001 .
15
b1001 1
b11 ,
1!
#103500
0!
#104000
b0 0
b0 3
02
0+
b0 .
05
b0 1
b0 ,
1!
#104100
1/
14
b111110001101000111000011100101 -
b11 $
b1100 '
b0 %
b101010010101 #
b111110001101000110011001010000 (
#104500
0!
#105000
b10011101110010110101111010111110 3
b0 #
b0 (
b0 '
b0 $
b10011101110010110101111010111110 %
b0 -
0/
b1100 0
1+
04
12
b111110001101000111000011100101 .
15
b1100 1
b11 ,
1!
#105500
0!
#106000
b0 0
b0 3
02
0+
b0 .
05
b0 1
b0 ,
1!
#106100
1/
14
b111100101101100111101011010100 -
b101 $
b1100 '
b0 %
b111101 #
b111100101101100111101010010111 (
#106500
0!
#107000
b10111100101 3
b0 #
b0 (
b0 '
b0 $
b10101110001010110000010111100101 %
b0 -
0/
b1100 0
1+
04
12
b111100101101100111101011010100 .
15
b1100 1
b101 ,
1!
#107500
0!
#108000
b0 0
b0 3
02
0+
b0 .
05
b0 1
b0 ,
1!
#108100
1/
14
b10000001000110100010000100101 -
b1 $
b10001 '
b0 %
b101100111110 #
b10000001000110011100011100111 (
#108500
0!
#109000
b1010101 3
b0 #
b0 (
b0 '
b0 $
b10110100000000110101010110000010 %
b0 -
0/
b10001 0
1+
04
12
b10000001000110100010000100101 .
15
b10001 1
b1 ,
1!
#109500
0!
#110000
b0 0
b0 3
02
0+
b0 .
05
b0 1
b0 ,
1!
#110100
b1010 '
b0 %
b11011011001 #
b11111010000111101110111101000 (
#110500
0!
#111000
b1010 1
1!
#111100
1/
14
b111011100100111000010110000 -
b101 $
b11001 '
b10001000111 #
b111011100100110110001101001 (
#111500
0!
#112000
b11001010111001 3
b0 #
b0 (
b0 '
b0 $
b1110010111100100011001010111001 %
b0 -
0/
b11001 0
1+
04
12
b111011100100111000010110000 .
15
b11001 1
b101 ,
1!
#112500
0!
#113000
b0 0
b0 3
02
0+
b0 .
05
b0 1
b0 ,
1!
#113100
b101 '
b0 %
b101111001010 #
b110010011100100000001111010011 (
#113500
0!
#114000
b101 1
1!
#114100
1/
14
b10110101011011011110110101111 -
b11 $
b1011 '
b11001111000 #
b10110101011011011011100110111 (
#114500
0!
#115000
b101001010010110101000110111101 3
b0 #
b0 (
b0 '
b0 $
b101001010010110101000110111101 %
b0 -
0/
b1011 0
1+
04
12
b10110101011011011110110101111 .
15
b1011 1
b11 ,
1!
#115500
0!
#116000
b0 0
b0 3
02
0+
b0 .
05
b0 1
b0 ,
1!
#116100
1/
14
b100010111010010011000000110101 -
b10 $
b11100 '
b0 %
b101010000111 #
b100010111010010010010110101110 (
#116500
0!
#117000
b11111111111111111110010011000000 3
b0 #
b0 (
b0 '
b0 $
b10010111001000001110010011000000 %
b0 -
0/
b11100 0
1+
04
12
b100010111010010011000000110101 .
15
b11100 1
b10 ,
1!
#117500
0!
#118000
b0 0
b0 3
02
0+
b0 .
05
b0 1
b0 ,
1!
#118100
1/
14
b100001111011110111001101011001 -
b1 $
b11101 '
b0 %
b10110010 #
b100001111011110111001010100111 (
#118500
0!
#119000
b10 3
b0 #
b0 (
b0 '
b0 $
b100111010000010000001011101100 %
b0 -
0/
b11101 0
1+
04
12
b100001111011110111001101011001 .
15
b11101 1
b1 ,
1!
#119500
0!
#120000
b0 0
b0 3
02
0+
b0 .
05
b0 1
b0 ,
1!
#120100
b10000 '
b0 %
b11100101 #
b11100000001101110001110111 (
#120500
0!
#121000
b10000 1
1!
#121100
1/
14
b10001010100010011111111011010 -
b10 $
b111100101101 #
b10001010100010011000010101101 (
#121500
0!
#122000
b11111111111111111011000100001110 3
b0 #
b0 (
b0 '
b0 $
b10110001000011101001000110001101 %
b0 -
0/
b10000 0
1+
04
12
b10001010100010011111111011010 .
15
b10 ,
1!
#122500
0!
#123000
b0 0
b0 3
02
0+
b0 .
05
b0 1
b0 ,
1!
#123100
b10010 '
b0 %
b100010000011 #
b10010110001101110111111111010 (
#123500
0!
#124000
b10010 1
1!
#124100
1/
14
b10110110100011011010010001101 -
b100 $
b1 '
b100110011110 #
b10110110100011010101011101111 (
#124500
0!
#125000
b10001110 3
b0 #
b0 (
b0 '
b0 $
b1010001000000101000111010101100 %
b0 -
0/
b1 0
1+
04
12
b10110110100011011010010001101 .
15
b1 1
b100 ,
1!
#125500
0!
#126000
b0 0
b0 3
02
0+
b0 .
05
b0 1
b0 ,
1!
#126100
b1000 '
b0 %
b111111001111 #
b101101101011000110101000000010 (
#126500
0!
#127000
b1000 1
1!
#127100
1/
14
b11010101001100011000111011101 -
b100 $
b10101 '
b11101101 #
b11010101001100011000011110000 (
#127500
0!
#128000
b10100010 3
b0 #
b0 (
b0 '
b0 $
b10111101000110011010001011101000 %
b0 -
0/
b10101 0
1+
04
12
b11010101001100011000111011101 .
15
b10101 1
b100 ,
1!
#128500
0!
#129000
b0 0
b0 3
02
0+
b0 .
05
b0 1
b0 ,
1!
#129100
b111 '
b0 %
b1000101111 #
b100110001100110110101010100110 (
#129500
0!
#130000
b111 1
1!
#130100
1/
14
b101001011111101111111001010110 -
b1 $
b1001 '
b110111001 #
b101001011111101111110010011101 (
#130500
0!
#131000
b11111111111111111111111110011001 3
b0 #
b0 (
b0 '
b0 $
b11110000100110010000000001000010 %
b0 -
0/
b1001 0
1+
04
12
b101001011111101111111001010110 .
15
b1001 1
b1 ,
1!
#131500
0!
